LICENSE
MANIFEST.in
README.rst
requirements.txt
setup.cfg
setup.py
crowdin/__init__.py
crowdin/api.py
crowdin/client.py
crowdin/main.py
crowdin_client.egg-info/PKG-INFO
crowdin_client.egg-info/SOURCES.txt
crowdin_client.egg-info/dependency_links.txt
crowdin_client.egg-info/not-zip-safe
crowdin_client.egg-info/requires.txt
crowdin_client.egg-info/top_level.txt
scripts/crowdin